{
    "x": 0,
    "y": 220,
    "width": 175,
    "height": 20,
    "action": {
        "type": "packmenu:open_url",
        "url": "https://wiki.enigmatica.net"
    },
    "icon": {
        "texture": "enigmatica:textures/wiki",
        "width": 175,
        "height": 20
    },
    "anchor": "top_left",
    "text": {
        "key": "packmenu.enigmatica.wiki"
    },
    "sprites": {
        "enabled": "enigmatica:icon/wiki",
        "enabled_focused": "enigmatica:icon/wiki_focused"
    }
}
